depict/__init__.py
depict/core/__init__.py
depict/core/config.py
depict/core/histogram.py
depict/core/line.py
depict/core/plot.py
depict/core/point.py
depict/core/session.py
depict/core/tools.py
depict/tools/__init__.py
depict/tools/color_palettes.py
depict-1.0.4.dist-info/LICENSE
depict-1.0.4.dist-info/METADATA
depict-1.0.4.dist-info/WHEEL
depict-1.0.4.dist-info/top_level.txt
depict-1.0.4.dist-info/RECORD
