Metadata-Version: 2.1
Name: depict
Version: 1.0.4
Summary: Business grade visualizations in seconds
Home-page: https://github.com/vboulanger/depict
Author: Victor Boulanger
Author-email: vb@live.fr
License: UNKNOWN
Platform: UNKNOWN
Classifier: Programming Language :: Python :: 3
Classifier: License :: OSI Approved :: MIT License
Classifier: Operating System :: OS Independent
Classifier: Development Status :: 5 - Production/Stable
Classifier: Natural Language :: English
Classifier: Topic :: Scientific/Engineering :: Visualization
Requires-Python: >=3.5
Requires-Dist: bokeh (>=2.0.0)
Requires-Dist: pandas (>=0.24.2)
Requires-Dist: seaborn (>=0.9.0)
Provides-Extra: doc
Requires-Dist: Sphinx ; extra == 'doc'
Provides-Extra: test
Requires-Dist: pycodestyle ; extra == 'test'
Requires-Dist: pytest ; extra == 'test'
